src/__init__.py
src/config.py
src/main.py
src/tools/__init__.py
src/tools/channel.py
src/tools/comments.py
src/tools/playlist.py
src/tools/search.py
src/tools/transcript.py
src/tools/video.py
src/youtube_client.py
youtube_connector_mcp-0.2.0.dist-info/METADATA
youtube_connector_mcp-0.2.0.dist-info/WHEEL
youtube_connector_mcp-0.2.0.dist-info/entry_points.txt
youtube_connector_mcp-0.2.0.dist-info/RECORD
