Metadata-Version: 2.4
Name: youtube-connector-mcp
Version: 0.2.0
Summary: YouTube MCP Server for Claude Code
License: MIT
Author: ShellyDeng08
Author-email: ShellyDeng08@users.noreply.github.com
Requires-Python: >=3.10
Classifier: License :: OSI Approved :: MIT License
Classifier: Programming Language :: Python :: 3
Classifier: Programming Language :: Python :: 3.10
Classifier: Programming Language :: Python :: 3.11
Classifier: Programming Language :: Python :: 3.12
Classifier: Programming Language :: Python :: 3.13
Classifier: Programming Language :: Python :: 3.14
Requires-Dist: google-api-python-client (>=2.140.0)
Requires-Dist: mcp (>=1.0.0)
Requires-Dist: pydantic (>=2.0.0)
Requires-Dist: youtube-transcript-api (>=0.6.0)
Project-URL: Documentation, https://github.com/ShellyDeng08/youtube-connector-mcp/blob/main/README.md
Project-URL: Homepage, https://github.com/ShellyDeng08/youtube-connector-mcp
Project-URL: Repository, https://github.com/ShellyDeng08/youtube-connector-mcp
